AUTHORS
LICENSE
MANIFEST.in
README
README.md
setup.py
lettuce_utils/__init__.py
lettuce_utils/cli.py
lettuce_utils/logger.py
lettuce_utils/waiter.py
lettuce_utils.egg-info/PKG-INFO
lettuce_utils.egg-info/SOURCES.txt
lettuce_utils.egg-info/dependency_links.txt
lettuce_utils.egg-info/entry_points.txt
lettuce_utils.egg-info/not-zip-safe
lettuce_utils.egg-info/requires.txt
lettuce_utils.egg-info/top_level.txt
lettuce_utils/steps/__init__.py
lettuce_utils/steps/common.py
lettuce_utils/steps/djangoify.py
lettuce_utils/steps/everything.py
lettuce_utils/steps/parsers.py
lettuce_utils/steps/browser/__init__.py
lettuce_utils/steps/browser/alerts.py
lettuce_utils/steps/browser/browsers.py
lettuce_utils/steps/browser/elements.py
lettuce_utils/steps/browser/finders.py
lettuce_utils/steps/browser/forms.py
lettuce_utils/steps/browser/javascript.py
lettuce_utils/steps/browser/mouse.py
lettuce_utils/steps/browser/navigation.py
lettuce_utils/steps/browser/page.py
lettuce_utils/terrains/__init__.py
lettuce_utils/terrains/browser.py
lettuce_utils/terrains/common.py
lettuce_utils/terrains/djangoify.py
lettuce_utils/terrains/everything.py
lettuce_utils/tests/__init__.py
lettuce_utils/tests/util.py