Metadata-Version: 1.1
Name: lettuce-utils
Version: 0.4.15
Summary: A nice mix of great BDD ingredients
Home-page: http://github.com/lettuceutils/lettuce_utils
Author: Simon Luijk
Author-email: simon@simonluijk.com
License: BSD
Platform: UNKNOWN
Classifier: Programming Language :: Python
Classifier: License :: OSI Approved :: BSD License
Classifier: Operating System :: OS Independent
Classifier: Development Status :: 4 - Beta
Classifier: Environment :: Web Environment
Classifier: Intended Audience :: Developers
Classifier: Topic :: Internet :: WWW/HTTP
Classifier: Topic :: Software Development :: Libraries :: Python Modules
